kalmankit/__init__.py
kalmankit/_version.py
kalmankit/extended.py
kalmankit/standard.py
kalmankit/utils.py
kalmankit-1.7.8.dist-info/METADATA
kalmankit-1.7.8.dist-info/WHEEL
kalmankit-1.7.8.dist-info/top_level.txt
kalmankit-1.7.8.dist-info/RECORD
