Metadata-Version: 2.1
Name: kalmankit
Version: 1.7.8
Summary: Multidimensional implementation of Kalman Filter algorithms
Home-page: https://github.com/Xylambda/kalmankit
Author: Alejandro Pérez-Sanjuán
Classifier: Development Status :: 3 - Alpha
Classifier: Intended Audience :: Developers
Classifier: Topic :: Software Development :: Build Tools
Classifier: License :: OSI Approved :: MIT License
Classifier: Programming Language :: Python :: 3
Classifier: Programming Language :: Python :: 3.6
Classifier: Programming Language :: Python :: 3.7
Classifier: Programming Language :: Python :: 3.8
Classifier: Programming Language :: Python :: 3 :: Only
Requires-Python: >=3.6, <4
Requires-Dist: numpy
